plotting/Atari_FPS_test.py
plotting/MinAtar_popgym_FPS_test.py
plotting/PArcade_gymnax_FPS_test.py
plotting/generate_analysis_data.py
plotting/noiseva.py
plotting/plot_fps.py
plotting/plottable.py
plotting/run_multi_seed_analysis.py
popgym_arcade/__init__.py
popgym_arcade/play.py
popgym_arcade/play_both.py
popgym_arcade/registration.py
popgym_arcade/train.py
popgym_arcade/wrappers.py
popgym_arcade/baselines/__init__.py
popgym_arcade/baselines/dqn.py
popgym_arcade/baselines/dqn_rnn.py
popgym_arcade/baselines/ppo.py
popgym_arcade/baselines/ppo_rnn.py
popgym_arcade/baselines/pqn.py
popgym_arcade/baselines/pqn_rnn.py
popgym_arcade/baselines/utils.py
popgym_arcade/baselines/model/__init__.py
popgym_arcade/baselines/model/builder.py
popgym_arcade/environments/__init__.py
popgym_arcade/environments/autoencode.py
popgym_arcade/environments/battleship.py
popgym_arcade/environments/breakout.py
popgym_arcade/environments/cartpole.py
popgym_arcade/environments/countrecall.py
popgym_arcade/environments/draw_utils.py
popgym_arcade/environments/minesweeper.py
popgym_arcade/environments/navigator.py
popgym_arcade/environments/skittles.py
popgym_arcade/environments/tetris.py
popgym_arcade-0.0.6.dist-info/licenses/LICENSE
tests/test_make_envs.py
tests/test_step_envs.py
tests/test_train.py
popgym_arcade-0.0.6.dist-info/METADATA
popgym_arcade-0.0.6.dist-info/WHEEL
popgym_arcade-0.0.6.dist-info/entry_points.txt
popgym_arcade-0.0.6.dist-info/top_level.txt
popgym_arcade-0.0.6.dist-info/RECORD
