Metadata-Version: 2.4
Name: popgym-arcade
Version: 0.0.6
Summary: POMDP Arcade Environments on the GPU
Author: Wang Zekang, He Zhe, Steven Morad
License: MIT License
Classifier: Programming Language :: Python :: 3
Classifier: License :: OSI Approved :: MIT License
Classifier: Operating System :: OS Independent
Requires-Python: >=3.10
License-File: LICENSE
Requires-Dist: stable-gymnax
Requires-Dist: dm_pix
Requires-Dist: jaxtyping
Provides-Extra: human
Requires-Dist: pygame-ce; extra == "human"
Provides-Extra: baselines
Requires-Dist: memax[equinox]; extra == "baselines"
Requires-Dist: optax; extra == "baselines"
Requires-Dist: equinox; extra == "baselines"
Requires-Dist: distreqx; extra == "baselines"
Requires-Dist: wandb[media]; extra == "baselines"
Requires-Dist: beartype; extra == "baselines"
Requires-Dist: jaxtyping; extra == "baselines"
Requires-Dist: imageio; extra == "baselines"
Provides-Extra: tests
Requires-Dist: pytest; extra == "tests"
Provides-Extra: all
Requires-Dist: pygame-ce; extra == "all"
Requires-Dist: memax[equinox]; extra == "all"
Requires-Dist: optax; extra == "all"
Requires-Dist: equinox; extra == "all"
Requires-Dist: distreqx; extra == "all"
Requires-Dist: wandb[media]; extra == "all"
Requires-Dist: beartype; extra == "all"
Requires-Dist: jaxtyping; extra == "all"
Requires-Dist: imageio; extra == "all"
Requires-Dist: pytest; extra == "all"
Dynamic: license-file
